[
  { "from": "2017-09-15T13:00:00", "name": "Trail Workshop (Erlebniscard)", "price": "kostenlos (**)", "url" : "forms/Infoblatt-Workshop-Erlebniscard-2017-09.pdf" },
  { "from": "2017-09-22T13:00:00", "name": "Trail Workshop (Erlebniscard)", "price": "kostenlos (**)", "url" : "forms/Infoblatt-Workshop-Erlebniscard-2017-09.pdf" },
  { "from": "2017-09-29T13:00:00", "name": "Trail Workshop (Erlebniscard)", "price": "kostenlos (**)", "url" : "forms/Infoblatt-Workshop-Erlebniscard-2017-09.pdf" },
  { "from": "2017-09-29", "to": "2017-10-01", "name": "Enduro Camp Soča", "price": "150 EUR", "url" : "forms/Infoblatt-Enduro Camp Soca.pdf" },
  { "from": "2017-10-06T13:00:00", "name": "Trail Workshop (Erlebniscard)", "price": "kostenlos (**)", "url" : "forms/Infoblatt-Workshop-Erlebniscard-2017-09.pdf" },
  { "from": "2017-10-13T13:00:00", "name": "Trail Workshop (Erlebniscard)", "price": "kostenlos (**)", "url" : "forms/Infoblatt-Workshop-Erlebniscard-2017-09.pdf" },
  { "from": "2017-10-20T13:00:00", "name": "Trail Workshop (Erlebniscard)", "price": "kostenlos (**)", "url" : "forms/Infoblatt-Workshop-Erlebniscard-2017-09.pdf" },
  { "from": "2017-10-27T13:00:00", "name": "Trail Workshop (Erlebniscard)", "price": "kostenlos (**)", "url" : "forms/Infoblatt-Workshop-Erlebniscard-2017-09.pdf" }
]